d3metafeatureextraction/__init__.py
d3metafeatureextraction/d3metafeatureextraction.py
d3metafeatureextraction-0.2.0.dist-info/DESCRIPTION.rst
d3metafeatureextraction-0.2.0.dist-info/METADATA
d3metafeatureextraction-0.2.0.dist-info/RECORD
d3metafeatureextraction-0.2.0.dist-info/WHEEL
d3metafeatureextraction-0.2.0.dist-info/dependency_links.txt
d3metafeatureextraction-0.2.0.dist-info/entry_points.txt
d3metafeatureextraction-0.2.0.dist-info/metadata.json
d3metafeatureextraction-0.2.0.dist-info/top_level.txt
