Metadata-Version: 2.0
Name: d3metafeatureextraction
Version: 0.2.0
Summary: A DARPA D3M wrapper for extracting dataset metafeatures using the byu-dml metalearn package.
Home-page: https://github.com/byu-dml/d3metafeatureextraction
Author: Roland Laboulaye, Brandon Schoenfeld
Author-email: rlaboulaye@gmail.com, bjschoenfeld@gmail.com
License: UNKNOWN
Download-URL: https://github.com/byu-dml/d3metafeatureextraction/archive/0.2.0.tar.gz
Keywords: metalearning,metafeature,machine learning,metalearn,d3m_primitive
Platform: UNKNOWN
Requires-Dist: metalearn (==0.3.0)
Requires-Dist: numpy
Requires-Dist: pandas
